{
 "actions": [],
 "allow_import": 1,
 "autoname": "naming_series:",
 "creation": "2026-04-26 18:00:00",
 "doctype": "DocType",
 "engine": "InnoDB",
 "field_order": [
  "naming_series",
  "flock_code",
  "farm",
  "house",
  "column_break_main",
  "breed_standard",
  "breed_code",
  "status",
  "section_break_dates",
  "placement_date",
  "expected_harvest_date",
  "harvest_date",
  "column_break_dates",
  "age_days",
  "cycle_number",
  "section_break_counts",
  "initial_count",
  "current_count",
  "mortality_total",
  "column_break_counts",
  "initial_weight_kg",
  "target_weight_kg",
  "current_avg_weight_kg",
  "section_break_source",
  "hatchery_source",
  "supplier",
  "purchase_invoice",
  "column_break_source",
  "unit_cost_per_chick",
  "total_placement_cost",
  "section_break_links",
  "project",
  "cost_center",
  "warehouse",
  "column_break_links",
  "live_bird_item",
  "assigned_laborer",
  "assigned_vet",
  "section_break_finance",
  "fcr_running",
  "mortality_pct",
  "feed_consumed_kg",
  "column_break_finance",
  "current_valuation",
  "is_archived",
  "archived_reason",
  "section_break_notes",
  "notes"
 ],
 "fields": [
  {"fieldname": "naming_series", "fieldtype": "Select", "label": "Series", "options": "FLK-.YYYY.-.####", "default": "FLK-.YYYY.-.####", "reqd": 1},
  {"fieldname": "flock_code", "fieldtype": "Data", "label": "Flock Code", "unique": 1, "in_list_view": 1, "in_global_search": 1},
  {"fieldname": "farm", "fieldtype": "Link", "label": "Farm", "options": "Farm", "reqd": 1, "in_list_view": 1, "in_standard_filter": 1},
  {"fieldname": "house", "fieldtype": "Link", "label": "Barn Name", "options": "Farm House", "in_standard_filter": 1, "in_list_view": 1, "description": "Select an existing barn or create a new one."},
  {"fieldname": "column_break_main", "fieldtype": "Column Break"},
  {"fieldname": "breed_standard", "fieldtype": "Link", "label": "Breed Standard", "options": "Breed Standard", "reqd": 1},
  {"fieldname": "breed_code", "fieldtype": "Data", "label": "Breed Code", "fetch_from": "breed_standard.breed_code", "read_only": 1},
  {"fieldname": "status", "fieldtype": "Select", "label": "Status", "options": "Planned\nActive\nHarvested\nArchived\nLost", "default": "Planned", "in_list_view": 1, "in_standard_filter": 1, "reqd": 1},
  {"fieldname": "section_break_dates", "fieldtype": "Section Break", "label": "Lifecycle"},
  {"fieldname": "placement_date", "fieldtype": "Date", "label": "Placement Date", "reqd": 1, "in_list_view": 1, "in_standard_filter": 1},
  {"fieldname": "expected_harvest_date", "fieldtype": "Date", "label": "Expected Harvest Date"},
  {"fieldname": "harvest_date", "fieldtype": "Date", "label": "Harvest Date"},
  {"fieldname": "column_break_dates", "fieldtype": "Column Break"},
  {"fieldname": "age_days", "fieldtype": "Int", "label": "Age (days)", "read_only": 1, "in_list_view": 1},
  {"fieldname": "cycle_number", "fieldtype": "Int", "label": "Cycle #"},
  {"fieldname": "section_break_counts", "fieldtype": "Section Break", "label": "Bird Counts"},
  {"fieldname": "initial_count", "fieldtype": "Int", "label": "Initial Count", "reqd": 1, "non_negative": 1},
  {"fieldname": "current_count", "fieldtype": "Int", "label": "Current Count", "read_only": 1, "in_list_view": 1},
  {"fieldname": "mortality_total", "fieldtype": "Int", "label": "Total Mortality", "read_only": 1, "default": "0"},
  {"fieldname": "column_break_counts", "fieldtype": "Column Break"},
  {"fieldname": "initial_weight_kg", "fieldtype": "Float", "label": "Initial Weight (kg)", "precision": "3", "default": "0"},
  {"fieldname": "target_weight_kg", "fieldtype": "Float", "label": "Target Weight (kg)", "precision": "3"},
  {"fieldname": "current_avg_weight_kg", "fieldtype": "Float", "label": "Current Avg Weight (kg)", "precision": "3", "read_only": 1},
  {"fieldname": "section_break_source", "fieldtype": "Section Break", "label": "Source"},
  {"fieldname": "hatchery_source", "fieldtype": "Data", "label": "Hatchery Source"},
  {"fieldname": "supplier", "fieldtype": "Link", "label": "Supplier", "options": "Supplier"},
  {"fieldname": "purchase_invoice", "fieldtype": "Link", "label": "Purchase Invoice", "options": "Purchase Invoice"},
  {"fieldname": "column_break_source", "fieldtype": "Column Break"},
  {"fieldname": "unit_cost_per_chick", "fieldtype": "Currency", "label": "Unit Cost / Chick"},
  {"fieldname": "total_placement_cost", "fieldtype": "Currency", "label": "Total Placement Cost", "read_only": 1},
  {"fieldname": "section_break_links", "fieldtype": "Section Break", "label": "ERPNext Links"},
  {"fieldname": "project", "fieldtype": "Link", "label": "Project", "options": "Project", "read_only": 1},
  {"fieldname": "cost_center", "fieldtype": "Link", "label": "Cost Center", "options": "Cost Center"},
  {"fieldname": "warehouse", "fieldtype": "Link", "label": "Warehouse", "options": "Warehouse"},
  {"fieldname": "column_break_links", "fieldtype": "Column Break"},
  {"fieldname": "live_bird_item", "fieldtype": "Link", "label": "Live Bird Item", "options": "Item", "description": "ERPNext Item representing live birds in this flock"},
  {"fieldname": "assigned_laborer", "fieldtype": "Link", "label": "Assigned Laborer", "options": "User"},
  {"fieldname": "assigned_vet", "fieldtype": "Link", "label": "Assigned Vet", "options": "User"},
  {"fieldname": "section_break_finance", "fieldtype": "Section Break", "label": "Performance / Finance"},
  {"fieldname": "fcr_running", "fieldtype": "Float", "label": "Running FCR", "precision": "2", "read_only": 1},
  {"fieldname": "mortality_pct", "fieldtype": "Percent", "label": "Mortality %", "read_only": 1},
  {"fieldname": "feed_consumed_kg", "fieldtype": "Float", "label": "Feed Consumed (kg)", "precision": "3", "read_only": 1, "default": "0"},
  {"fieldname": "column_break_finance", "fieldtype": "Column Break"},
  {"fieldname": "current_valuation", "fieldtype": "Currency", "label": "Current Valuation", "read_only": 1},
  {"fieldname": "is_archived", "fieldtype": "Check", "label": "Archived", "default": "0"},
  {"fieldname": "archived_reason", "fieldtype": "Small Text", "label": "Archive Reason", "depends_on": "is_archived"},
  {"fieldname": "section_break_notes", "fieldtype": "Section Break", "label": "Notes"},
  {"fieldname": "notes", "fieldtype": "Text", "label": "Notes"}
 ],
 "links": [
  {"link_doctype": "Flock Daily Log", "link_fieldname": "flock"},
  {"link_doctype": "Flock Feed Entry", "link_fieldname": "flock"},
  {"link_doctype": "Flock Weigh-in", "link_fieldname": "flock"},
  {"link_doctype": "Mortality Event", "link_fieldname": "flock"},
  {"link_doctype": "Treatment Round", "link_fieldname": "flock"},
  {"link_doctype": "Health Record", "link_fieldname": "flock"},
  {"link_doctype": "Slaughter Event", "link_fieldname": "flock"},
  {"link_doctype": "Poultry Sales Order", "link_fieldname": "flock"},
  {"link_doctype": "Flock Snapshot", "link_fieldname": "flock"}
 ],
 "modified": "2026-04-26 18:00:00",
 "modified_by": "Administrator",
 "module": "Farm Manager",
 "name": "Flock",
 "owner": "Administrator",
 "permissions": [
  {"role": "System Manager", "create": 1, "delete": 1, "email": 1, "export": 1, "print": 1, "read": 1, "report": 1, "share": 1, "write": 1},
  {"role": "Farm Manager", "create": 1, "delete": 0, "email": 1, "export": 1, "print": 1, "read": 1, "report": 1, "share": 1, "write": 1},
  {"role": "Farm Veterinarian", "read": 1, "write": 1, "report": 1, "print": 1},
  {"role": "Farm Laborer", "read": 1, "report": 1, "if_owner": 0},
  {"role": "Farm Accountant", "read": 1, "report": 1, "print": 1, "export": 1}
 ],
 "search_fields": "flock_code,farm,house,breed_code,status",
 "sort_field": "placement_date",
 "sort_order": "DESC",
 "title_field": "flock_code",
 "track_changes": 1
}
